oasa/__init__.py
oasa/atom.py
oasa/bond.py
oasa/cairo_out.py
oasa/cdml.py
oasa/chem_vertex.py
oasa/common.py
oasa/config.py
oasa/converter_base.py
oasa/coords_generator.py
oasa/coords_optimizer.py
oasa/dom_extensions.py
oasa/geometry.py
oasa/inchi.py
oasa/inchi_key.py
oasa/isotope_database.py
oasa/known_groups.py
oasa/linear_formula.py
oasa/misc.py
oasa/molecule.py
oasa/molfile.py
oasa/name_database.py
oasa/oasa_exceptions.py
oasa/periodic_table.py
oasa/plugin.py
oasa/pybel_bridge.py
oasa/query_atom.py
oasa/reaction.py
oasa/smiles.py
oasa/stereochemistry.py
oasa/structure_database.py
oasa/subsearch.py
oasa/subsearch_data.py
oasa/svg_out.py
oasa/transform.py
oasa/transform3d.py
oasa/graph/__init__.py
oasa/graph/basic.py
oasa/graph/diedge.py
oasa/graph/digraph.py
oasa/graph/edge.py
oasa/graph/graph.py
oasa/graph/vertex.py
oasa3-0.14.1.dist-info/LICENSE
oasa3-0.14.1.dist-info/METADATA
oasa3-0.14.1.dist-info/WHEEL
oasa3-0.14.1.dist-info/top_level.txt
oasa3-0.14.1.dist-info/RECORD
