Metadata-Version: 2.1
Name: oasa3
Version: 0.14.1
Summary: OASA is a free cheminformatics library written in Python
Author: Beda Kosata
Author-email: beda@zirael.org
Maintainer: Reinis Danne
Maintainer-email: rei4dan@gmail.com
License: GNU GPL
Project-URL: Website, http://bkchem.zirael.org/oasa_en.html
Project-URL: Git repository, https://gitlab.com/oasa/oasa
Platform: Unix
Platform: Windows
Platform: hopefully other OSes able to run Python
Classifier: Programming Language :: Python :: 2
Classifier: Programming Language :: Python :: 3
Classifier: License :: OSI Approved :: GNU General Public License v2 (GPLv2)
Classifier: Operating System :: Microsoft :: Windows
Classifier: Operating System :: Unix
Requires-Python: >=2.6
License-File: LICENSE
Requires-Dist: pycairo
